tuw_nlp/__init__.py
tuw_nlp/utils.py
tuw_nlp/__pycache__/__init__.cpython-310.pyc
tuw_nlp/__pycache__/__init__.cpython-37.pyc
tuw_nlp/__pycache__/__init__.cpython-39.pyc
tuw_nlp/__pycache__/utils.cpython-310.pyc
tuw_nlp/__pycache__/utils.cpython-37.pyc
tuw_nlp/__pycache__/utils.cpython-39.pyc
tuw_nlp/common/__init__.py
tuw_nlp/common/eval.py
tuw_nlp/common/utils.py
tuw_nlp/common/vocabulary.py
tuw_nlp/common/__pycache__/__init__.cpython-310.pyc
tuw_nlp/common/__pycache__/__init__.cpython-37.pyc
tuw_nlp/common/__pycache__/__init__.cpython-39.pyc
tuw_nlp/common/__pycache__/eval.cpython-39.pyc
tuw_nlp/common/__pycache__/utils.cpython-310.pyc
tuw_nlp/common/__pycache__/utils.cpython-37.pyc
tuw_nlp/common/__pycache__/utils.cpython-39.pyc
tuw_nlp/common/__pycache__/vocabulary.cpython-310.pyc
tuw_nlp/common/__pycache__/vocabulary.cpython-37.pyc
tuw_nlp/common/__pycache__/vocabulary.cpython-39.pyc
tuw_nlp/grammar/__init__.py
tuw_nlp/grammar/alto.py
tuw_nlp/grammar/irtg.py
tuw_nlp/grammar/lexicon.py
tuw_nlp/grammar/propositions.txt
tuw_nlp/grammar/sorted_train_edges_mapped
tuw_nlp/grammar/text_to_4lang.py
tuw_nlp/grammar/text_to_amr.py
tuw_nlp/grammar/text_to_drs.py
tuw_nlp/grammar/text_to_ndrs.py
tuw_nlp/grammar/text_to_sdp.py
tuw_nlp/grammar/text_to_ucca.py
tuw_nlp/grammar/text_to_ud.py
tuw_nlp/grammar/ud_fl.py
tuw_nlp/grammar/utils.py
tuw_nlp/grammar/__pycache__/__init__.cpython-310.pyc
tuw_nlp/grammar/__pycache__/__init__.cpython-37.pyc
tuw_nlp/grammar/__pycache__/__init__.cpython-39.pyc
tuw_nlp/grammar/__pycache__/alto.cpython-310.pyc
tuw_nlp/grammar/__pycache__/alto.cpython-37.pyc
tuw_nlp/grammar/__pycache__/alto.cpython-39.pyc
tuw_nlp/grammar/__pycache__/irtg.cpython-310.pyc
tuw_nlp/grammar/__pycache__/irtg.cpython-37.pyc
tuw_nlp/grammar/__pycache__/irtg.cpython-39.pyc
tuw_nlp/grammar/__pycache__/lexicon.cpython-310.pyc
tuw_nlp/grammar/__pycache__/lexicon.cpython-37.pyc
tuw_nlp/grammar/__pycache__/lexicon.cpython-39.pyc
tuw_nlp-0.1.0.dist-info/LICENSE
tuw_nlp-0.1.0.dist-info/METADATA
tuw_nlp-0.1.0.dist-info/WHEEL
tuw_nlp-0.1.0.dist-info/top_level.txt
tuw_nlp-0.1.0.dist-info/RECORD
