Metadata-Version: 2.1
Name: tuw-nlp
Version: 0.1.0
Summary: NLP tools at TUW Informatics
Home-page: http://github.com/recski/tuw-nlp
Author: Gabor Recski, Adam Kovacs
Author-email: gabor.recski@tuwien.ac.at,adam.kovacs@tuwien.ac.at
License: MIT
Keywords: NLP graph transformation explainable AI XAI semantic graphs
Platform: UNKNOWN
Classifier: Development Status :: 3 - Alpha
Classifier: Intended Audience :: Science/Research
Classifier: Intended Audience :: Developers
Classifier: License :: OSI Approved :: MIT License
Classifier: Programming Language :: Python :: 3
License-File: LICENSE
Requires-Dist: dict-recursive-update
Requires-Dist: networkx
Requires-Dist: penman
Requires-Dist: stanza (==1.3.0)
Requires-Dist: nltk
Requires-Dist: graphviz
Requires-Dist: conceptnet-lite
Requires-Dist: pywsd
Requires-Dist: supar
Requires-Dist: amrlib
Requires-Dist: word2number
Requires-Dist: unidecode
Requires-Dist: conllu
Requires-Dist: tabulate
